<root annotationID="0" passageID="905001">
  <attributes />
  <layer layerID="0">
    <attributes />
    <extra doc="[[]]" />
    <node ID="0.1" type="Punctuation">
      <attributes paragraph="1" paragraph_position="1" text="&quot;" />
      <extra orig_paragraph="1" />
    </node>
    <node ID="0.2" type="Punctuation">
      <attributes paragraph="1" paragraph_position="2" text="&quot;" />
      <extra orig_paragraph="1" />
    </node>
    <node ID="0.3" type="Word">
      <attributes paragraph="1" paragraph_position="3" text="About" />
      <extra orig_paragraph="1" />
    </node>
    <node ID="0.4" type="Word">
      <attributes paragraph="1" paragraph_position="4" text="17,000" />
      <extra orig_paragraph="1" />
    </node>
    <node ID="0.5" type="Punctuation">
      <attributes paragraph="1" paragraph_position="5" text="." />
      <extra orig_paragraph="1" />
    </node>
  </layer>
  <layer layerID="1">
    <attributes />
    <node ID="1.1" type="FN">
      <attributes />
      <edge toID="1.2" type="H">
        <attributes />
      </edge>
    </node>
    <node ID="1.2" type="FN">
      <attributes />
      <edge toID="1.6" type="P">
        <attributes />
      </edge>
      <edge toID="1.7" type="A">
        <attributes />
      </edge>
      <edge toID="1.8" type="A">
        <attributes />
      </edge>
    </node>
    <node ID="1.6" type="FN">
      <attributes implicit="True" />
    </node>
    <node ID="1.7" type="FN">
      <attributes implicit="True" />
    </node>
    <node ID="1.8" type="FN">
      <attributes />
      <edge toID="1.9" type="S">
        <attributes />
      </edge>
      <edge toID="1.10" type="A">
        <attributes />
      </edge>
      <edge toID="1.11" type="D">
        <attributes />
      </edge>
      <edge toID="1.12" type="A">
        <attributes />
      </edge>
      <edge toID="1.13" type="U">
        <attributes />
      </edge>
      <edge toID="1.14" type="U">
        <attributes />
      </edge>
      <edge toID="1.15" type="U">
        <attributes />
      </edge>
    </node>
    <node ID="1.9" type="FN">
      <attributes implicit="True" />
    </node>
    <node ID="1.10" type="FN">
      <attributes implicit="True" />
    </node>
    <node ID="1.11" type="FN">
      <attributes />
      <edge toID="0.3" type="Terminal">
        <attributes />
      </edge>
    </node>
    <node ID="1.12" type="FN">
      <attributes />
      <edge toID="0.4" type="Terminal">
        <attributes />
      </edge>
    </node>
    <node ID="1.13" type="PNCT">
      <attributes />
      <edge toID="0.1" type="Terminal">
        <attributes />
      </edge>
    </node>
    <node ID="1.14" type="PNCT">
      <attributes />
      <edge toID="0.2" type="Terminal">
        <attributes />
      </edge>
    </node>
    <node ID="1.15" type="PNCT">
      <attributes />
      <edge toID="0.5" type="Terminal">
        <attributes />
      </edge>
    </node>
  </layer>
</root>
